slisemap_interactive/__init__.py
slisemap_interactive/__main__.py
slisemap_interactive/app.py
slisemap_interactive/layout.py
slisemap_interactive/load.py
slisemap_interactive/plots.py
slisemap_interactive/xiplot.py
slisemap_interactive-0.6.0.dist-info/LICENSE
slisemap_interactive-0.6.0.dist-info/METADATA
slisemap_interactive-0.6.0.dist-info/WHEEL
slisemap_interactive-0.6.0.dist-info/entry_points.txt
slisemap_interactive-0.6.0.dist-info/top_level.txt
slisemap_interactive-0.6.0.dist-info/RECORD
