Metadata-Version: 2.1
Name: slisemap_interactive
Version: 0.6.0
Summary: Interactive plots for Slisemap using Dash
Author-email: Anton Björklund <anton.bjorklund@helsinki.fi>
License: MIT
Project-URL: github, https://github.com/edahelsinki/slisemap_interactive
Keywords: Slisemap,XAI,visualization,interactive
Classifier: Programming Language :: Python :: 3
Classifier: License :: OSI Approved :: MIT License
Classifier: Framework :: Dash
Classifier: Topic :: Scientific/Engineering :: Visualization
License-File: LICENSE
Requires-Dist: numpy >=1.19
Requires-Dist: dash >=2.6
Requires-Dist: pandas >=1.4
Requires-Dist: plotly >=5.9
Requires-Dist: scipy >=1.2
Requires-Dist: slisemap >=1.4 ; platform_system != "Emscripten"
Requires-Dist: jupyter-dash >=0.4 ; platform_system != "Emscripten"
Provides-Extra: dev
Requires-Dist: pytest ; extra == 'dev'
Requires-Dist: pytest-cov ; extra == 'dev'
Requires-Dist: black[jupyter] ; extra == 'dev'
Requires-Dist: ruff ; extra == 'dev'
Requires-Dist: jupyter ; extra == 'dev'
Requires-Dist: IPython ; extra == 'dev'
Provides-Extra: xiplot
Requires-Dist: xiplot ; extra == 'xiplot'
